{
  "commonName": "Asparagus",
  "cycle": "PERENNIAL",
  "sunNeeds": "FULL_SUN",
  "waterNeeds": "MODERATE",
  "rootDepth": "DEEP",
  "growthHabit": "LEAF",
  "soilTempMinF": null,
  "soilTempOptimalF": null,
  "frostTolerant": true,
  "spacingMin": 12,
  "spacingMax": 18,
  "plantingDepthInches": 6,
  "containerSuitable": false,
  "requiresStaking": false,
  "requiresPruning": false,
  "edibleParts": ["stem"],
  "daysToMaturityMin": null,
  "daysToMaturityMax": null,
  "wateringInchesPerWeek": 1.5,
  "fertilizingFrequencyWeeks": null,
  "mulchRecommended": true,
  "notes": "Perennial crop. Don't harvest first 2 years. Plant crowns deeply in trenches. Gentle hand-weeding needed to avoid disturbing roots. Full production by year 3."
}
